xttp/__init__.py
xttp/client.py
xttp/exceptions.py
xttp/rate_limit_config.py
xttp/rate_limiter.py
xttp/request.py
xttp-0.1.0.dist-info/METADATA
xttp-0.1.0.dist-info/WHEEL
xttp-0.1.0.dist-info/RECORD
