Metadata-Version: 2.4
Name: xttp
Version: 0.1.0
Summary: Async HTTP client with retry, rate limiting, and modern features
Project-URL: Homepage, https://github.com/ackness/xttp
Project-URL: Repository, https://github.com/ackness/xttp
Project-URL: Issues, https://github.com/ackness/xttp/issues
Author-email: ackness <ackness8@gmail.com>
License: MIT
Keywords: async,client,fluent-api,http,httpx,rate-limit,retry
Classifier: Development Status :: 4 - Beta
Classifier: Intended Audience :: Developers
Classifier: License :: OSI Approved :: MIT License
Classifier: Programming Language :: Python :: 3
Classifier: Programming Language :: Python :: 3.13
Classifier: Topic :: Internet :: WWW/HTTP
Classifier: Topic :: Software Development :: Libraries :: Python Modules
Classifier: Typing :: Typed
Requires-Python: >=3.13
Requires-Dist: httpx>=0.28.1
Requires-Dist: loguru>=0.7.3
